telexception/__init__.py
telexception/telexception.py
telexception-1.0.0.dist-info/METADATA
telexception-1.0.0.dist-info/WHEEL
telexception-1.0.0.dist-info/top_level.txt
telexception-1.0.0.dist-info/RECORD
