Metadata-Version: 2.1
Name: telexception
Version: 1.0.0
Summary: A Python module that sends exception messages to Telegram
Home-page: https://github.com/UrNickName16/Telexception/
Author: Andrey Zotov
Classifier: Programming Language :: Python :: 3.7
Requires-Dist: ipython (>=7)
Requires-Dist: requests (>=2)
